{"AC":{"p":"ಅಸೆನ್ಶನ್ ದ್ವೀಪ"},"AD":{"p":"ಅಂಡೋರಾ"},"AE":{"p":"ಸಂಯುಕ್ತ ಅರಬ್ ಎಮಿರೇಟಸ್"},"AF":{"p":"ಅಫಘಾನಿಸ್ಥಾನ್"},"AG":{"p":"ಆಂಟಿಗುವಾ ಮತ್ತು ಬರ್ಬುಡಾ"},"AI":{"p":"ಆಂಗ್ವಿಲ್ಲಾ"},"AL":{"p":"ಅಲ್ಬೇನಿಯಾ"},"AM":{"p":"ಅರ್ಮೇನಿಯಾ"},"AO":{"p":"ಅಂಗೋಲಾ"},"AQ":{"p":"ಅಂಟಾರ್ಟಿಕಾ"},"AR":{"p":"ಅರ್ಜೆಂಟಿನಾ"},"AS":{"p":"ಅಮೇರಿಕನ್ ಸಮೋವಾ"},"AT":{"p":"ಆಸ್ಟ್ರಿಯಾ"},"AU":{"p":"ಆಸ್ಟ್ರೇಲಿಯ"},"AW":{"p":"ಅರುಬಾ"},"AX":{"p":"ಆಲ್ಯಾಂಡ್ ದ್ವೀಪಗಳು"},"AZ":{"p":"ಅಜರ್ಬೈಜಾನ್"},"BA":{"p":"ಬೋಸ್ನಿಯಾ ಮತ್ತು ಹರ್ಜೆಗೋವಿನಾ"},"BB":{"p":"ಬಾರ್ಬಡೋಸ್"},"BD":{"p":"ಬಾಂಗ್ಲಾದೇಶ್"},"BE":{"p":"ಬೆಲ್ಜಿಯಮ್"},"BF":{"p":"ಬುರ್ಕಿನಾ ಫಾಸೋ"},"BG":{"p":"ಬಲ್ಗೇರಿಯಾ"},"BH":{"p":"ಬಹ್ರೇನ್"},"BI":{"p":"ಬುರುಂಡಿ"},"BJ":{"p":"ಬೆನಿನ್"},"BL":{"p":"ಸೇಂಟ್ ಬಾರ್ಥೆಲೆಮಿ"},"BM":{"p":"ಬರ್ಮುಡಾ"},"BN":{"p":"ಬ್ರೂನಿ"},"BO":{"p":"ಬೊಲಿವಿಯಾ"},"BQ":{"p":"ಕೆರೀಬಿಯನ್ ನೆದರ್‌ಲ್ಯಾಂಡ್ಸ್"},"BR":{"p":"ಬ್ರೆಜಿಲ್"},"BS":{"p":"ಬಹಾಮಾಸ್"},"BT":{"p":"ಭೂತಾನ್"},"BV":{"p":"ಬೋವೆಟ್ ದ್ವೀಪ"},"BW":{"p":"ಬೋಟ್ಸ್‌ವಾನಾ"},"BY":{"p":"ಬೆಲಾರಸ್"},"BZ":{"p":"ಬೆಲಿಜ್"},"CA":{"p":"ಕೆನಡಾ"},"CC":{"p":"ಕೊಕೊಸ್ (ಕೀಲಿಂಗ್) ದ್ವೀಪಗಳು"},"CD":{"p":"ಕಾಂಗೋ - ಕಿನ್ಶಾಸಾ","v":"ಕಾಂಗೋ (DRC)"},"CF":{"p":"ಮಧ್ಯ ಆಫ್ರಿಕಾ ಗಣರಾಜ್ಯ"},"CG":{"p":"ಕಾಂಗೋ - ಬ್ರಾಜಾವಿಲ್ಲೇ","v":"ಕಾಂಗೋ (ಗಣರಾಜ್ಯ)"},"CH":{"p":"ಸ್ವಿಟ್ಜರ್ಲ್ಯಾಂಡ್"},"CI":{"p":"ಕೋತ್‌ ದಿವಾರ್‍","v":"ಐವರಿ ಕೋಸ್ಟ್"},"CK":{"p":"ಕುಕ್ ದ್ವೀಪಗಳು"},"CL":{"p":"ಚಿಲಿ"},"CM":{"p":"ಕ್ಯಾಮರೋನ್"},"CN":{"p":"ಚೀನಾ"},"CO":{"p":"ಕೊಲಂಬಿಯಾ"},"CP":{"p":"ಕ್ಲಿಪ್ಪರ್‌ಟಾನ್ ದ್ವೀಪಗಳು"},"CR":{"p":"ಕೊಸ್ಟಾ ರಿಕಾ"},"CU":{"p":"ಕ್ಯೂಬಾ"},"CV":{"p":"ಕೇಪ್ ವರ್ಡೆ"},"CW":{"p":"ಕುರಾಕಾವ್"},"CX":{"p":"ಕ್ರಿಸ್ಮಸ್ ದ್ವೀಪ"},"CY":{"p":"ಸೈಪ್ರಸ್"},"CZ":{"p":"ಝೆಕಿಯಾ","v":"ಝೆಕ್ ರಿಪಬ್ಲಿಕ್"},"DE":{"p":"ಜರ್ಮನಿ"},"DG":{"p":"ಡೈಗೋ ಗಾರ್ಸಿಯ"},"DJ":{"p":"ಜಿಬೋಟಿ"},"DK":{"p":"ಡೆನ್ಮಾರ್ಕ್"},"DM":{"p":"ಡೊಮಿನಿಕಾ"},"DO":{"p":"ಡೊಮೆನಿಕನ್ ರಿಪಬ್ಲಿಕ್"},"DZ":{"p":"ಅಲ್ಗೇರಿಯಾ"},"EA":{"p":"ಸೆಯುಟಾ ಹಾಗೂ ಮೆಲಿಲ್ಲಾ"},"EC":{"p":"ಈಕ್ವೆಡಾರ್"},"EE":{"p":"ಎಸ್ಟೋನಿಯಾ"},"EG":{"p":"ಈಜಿಪ್ಟ್"},"EH":{"p":"ಪಶ್ಚಿಮ ಸಹಾರಾ"},"ER":{"p":"ಏರಿಟ್ರಿಯಾ"},"ES":{"p":"ಸ್ಪೇನ್"},"ET":{"p":"ಇಥಿಯೋಪಿಯಾ"},"EU":{"p":"ಯುರೋಪಿಯನ್ ಒಕ್ಕೂಟ"},"EZ":{"p":"EZ"},"FI":{"p":"ಫಿನ್‌ಲ್ಯಾಂಡ್"},"FJ":{"p":"ಫಿಜಿ"},"FK":{"p":"ಫಾಲ್ಕ್‌ಲ್ಯಾಂಡ್ ದ್ವೀಪಗಳು","v":"ಫಾಲ್ಕ್‌ಲ್ಯಾಂಡ್ ದ್ವೀಪಗಳು (ಇಸ್ಲಾಸ್ ಮಾಲ್ವಿನಸ್)"},"FM":{"p":"ಮೈಕ್ರೋನೇಶಿಯಾ"},"FO":{"p":"ಫರೋ ದ್ವೀಪಗಳು"},"FR":{"p":"ಫ್ರಾನ್ಸ್"},"GA":{"p":"ಗೆಬೊನ್"},"GB":{"p":"ಬ್ರಿಟನ್/ಇಂಗ್ಲೆಂಡ್","s":"ಯು.ಕೆ."},"GD":{"p":"ಗ್ರೆನೆಡಾ"},"GE":{"p":"ಜಾರ್ಜಿಯಾ"},"GF":{"p":"ಫ್ರೆಂಚ್ ಗಯಾನಾ"},"GG":{"p":"ಗುರ್ನ್‌ಸೆ"},"GH":{"p":"ಘಾನಾ"},"GI":{"p":"ಗಿಬ್ರಾಲ್ಟರ್"},"GL":{"p":"ಗ್ರೀನ್‌ಲ್ಯಾಂಡ್"},"GM":{"p":"ಗ್ಯಾಂಬಿಯಾ"},"GN":{"p":"ಗಿನಿ"},"GP":{"p":"ಗುಡೆಲೋಪ್"},"GQ":{"p":"ಈಕ್ವೆಟೋರಿಯಲ್ ಗಿನಿ"},"GR":{"p":"ಗ್ರೀಸ್"},"GS":{"p":"ದಕ್ಷಿಣ ಜಾರ್ಜಿಯಾ ಮತ್ತು ದಕ್ಷಿಣ ಸ್ಯಾಂಡ್‍ವಿಚ್ ದ್ವೀಪಗಳು"},"GT":{"p":"ಗ್ವಾಟೆಮಾಲಾ"},"GU":{"p":"ಗುಯಾಮ್"},"GW":{"p":"ಗಿನಿ-ಬಿಸ್ಸಾವ್"},"GY":{"p":"ಗಯಾನಾ"},"HK":{"p":"ಹಾಂಗ್ ಕಾಂಗ್ SAR ಚೈನಾ","s":"ಹಾಂಗ್ ಕಾಂಗ್"},"HM":{"p":"ಹರ್ಡ್ ಮತ್ತು ಮ್ಯಾಕ್‌ಡೋನಾಲ್ಡ್ ದ್ವೀಪಗಳು"},"HN":{"p":"ಹೊಂಡುರಾಸ್"},"HR":{"p":"ಕ್ರೊಯೇಶಿಯಾ"},"HT":{"p":"ಹೈಟಿ"},"HU":{"p":"ಹಂಗೇರಿ"},"IC":{"p":"ಕ್ಯಾನರಿ ದ್ವೀಪಗಳು"},"ID":{"p":"ಇಂಡೋನೇಶಿಯಾ"},"IE":{"p":"ಐರ್ಲೆಂಡ್"},"IL":{"p":"ಇಸ್ರೇಲ್"},"IM":{"p":"ಐಲ್ ಆಫ್ ಮ್ಯಾನ್"},"IN":{"p":"ಭಾರತ"},"IO":{"p":"ಬ್ರಿಟೀಷ್ ಹಿಂದೂ ಮಹಾಸಾಗರದ ಪ್ರದೇಶ"},"IQ":{"p":"ಇರಾಕ್"},"IR":{"p":"ಇರಾನ್"},"IS":{"p":"ಐಸ್‌ಲ್ಯಾಂಡ್"},"IT":{"p":"ಇಟಲಿ"},"JE":{"p":"ಜೆರ್ಸಿ"},"JM":{"p":"ಜಮೈಕಾ"},"JO":{"p":"ಜೋರ್ಡಾನ್"},"JP":{"p":"ಜಪಾನ್"},"KE":{"p":"ಕೀನ್ಯಾ"},"KG":{"p":"ಕಿರ್ಗಿಸ್ಥಾನ್"},"KH":{"p":"ಕಾಂಬೋಡಿಯಾ"},"KI":{"p":"ಕಿರಿಬಾತಿ"},"KM":{"p":"ಕೊಮೊರೊಸ್"},"KN":{"p":"ಸೇಂಟ್ ಕಿಟ್ಸ್ ಮತ್ತು ನೆವಿಸ್"},"KP":{"p":"ಉತ್ತರ ಕೋರಿಯಾ"},"KR":{"p":"ದಕ್ಷಿಣ ಕೋರಿಯಾ"},"KW":{"p":"ಕುವೈತ್"},"KY":{"p":"ಕೇಮನ್ ದ್ವೀಪಗಳು"},"KZ":{"p":"ಕಝಾಕಿಸ್ಥಾನ್"},"LA":{"p":"ಲಾವೋಸ್"},"LB":{"p":"ಲೆಬನಾನ್"},"LC":{"p":"ಸೇಂಟ್ ಲೂಸಿಯಾ"},"LI":{"p":"ಲಿಚೆನ್‌ಸ್ಟೈನ್"},"LK":{"p":"ಶ್ರೀಲಂಕಾ"},"LR":{"p":"ಲಿಬೇರಿಯಾ"},"LS":{"p":"ಲೆಸೊಥೋ"},"LT":{"p":"ಲಿಥುವೇನಿಯಾ"},"LU":{"p":"ಲಕ್ಸಂಬರ್ಗ್"},"LV":{"p":"ಲಾಟ್ವಿಯಾ"},"LY":{"p":"ಲಿಬಿಯಾ"},"MA":{"p":"ಮೊರಾಕ್ಕೊ"},"MC":{"p":"ಮೊನಾಕೊ"},"MD":{"p":"ಮೊಲ್ಡೋವಾ"},"ME":{"p":"ಮೊಂಟೆನೆಗ್ರೋ"},"MF":{"p":"ಸೇಂಟ್ ಮಾರ್ಟಿನ್"},"MG":{"p":"ಮಡಗಾಸ್ಕರ್"},"MH":{"p":"ಮಾರ್ಷಲ್ ದ್ವೀಪಗಳು"},"MK":{"p":"ಮ್ಯಾಸಿಡೋನಿಯಾ","v":"ಮ್ಯಾಸಿಡೋನಿಯ (FYROM)"},"ML":{"p":"ಮಾಲಿ"},"MM":{"p":"ಮಯನ್ಮಾರ್ (ಬರ್ಮಾ)"},"MN":{"p":"ಮೊಂಗೋಲಿಯಾ"},"MO":{"p":"ಮಖಾವು (SAR) ಚೈನಾ","s":"ಮಖಾವು"},"MP":{"p":"ಉತ್ತರ ಮರಿಯಾನಾ ದ್ವೀಪಗಳು"},"MQ":{"p":"ಮಾರ್ಟಿನಿಕ್"},"MR":{"p":"ಮಾರಿಟೇನಿಯಾ"},"MS":{"p":"ಮಾಂಟ್‌ಸೆರೇಟ್"},"MT":{"p":"ಮಾಲ್ಟಾ"},"MU":{"p":"ಮಾರಿಷಸ್"},"MV":{"p":"ಮಾಲ್ಡಿವ್ಸ್"},"MW":{"p":"ಮಲಾವಿ"},"MX":{"p":"ಮೆಕ್ಸಿಕೊ"},"MY":{"p":"ಮಲೇಶಿಯಾ"},"MZ":{"p":"ಮೊಜಾಂಬಿಕ್"},"NA":{"p":"ನಮೀಬಿಯಾ"},"NC":{"p":"ನ್ಯೂ ಕ್ಯಾಲಿಡೋನಿಯಾ"},"NE":{"p":"ನೈಜರ್"},"NF":{"p":"ನಾರ್ಫೋಕ್ ದ್ವೀಪ"},"NG":{"p":"ನೈಜೀರಿಯಾ"},"NI":{"p":"ನಿಕಾರಾಗುವಾ"},"NL":{"p":"ನೆದರ್‌ಲ್ಯಾಂಡ್ಸ್"},"NO":{"p":"ನಾರ್ವೇ"},"NP":{"p":"ನೇಪಾಳ"},"NR":{"p":"ನೌರು"},"NU":{"p":"ನಿಯು"},"NZ":{"p":"ನ್ಯೂಜಿಲೆಂಡ್"},"OM":{"p":"ಓಮನ್"},"PA":{"p":"ಪನಾಮಾ"},"PE":{"p":"ಪೆರು"},"PF":{"p":"ಫ್ರೆಂಚ್ ಪಾಲಿನೇಷ್ಯಾ"},"PG":{"p":"ಪಪುವಾ ನ್ಯೂಗಿನಿಯಾ"},"PH":{"p":"ಫಿಲಿಫೈನ್ಸ್"},"PK":{"p":"ಪಾಕಿಸ್ತಾನ"},"PL":{"p":"ಪೋಲ್ಯಾಂಡ್"},"PM":{"p":"ಸೇಂಟ್ ಪಿಯರೆ ಮತ್ತು ಮಿಕೆಲನ್"},"PN":{"p":"ಪಿಟ್‌ಕೈರ್ನ್ ದ್ವೀಪಗಳು"},"PR":{"p":"ಪ್ಯೂರ್ಟೋ ರಿಕೊ"},"PS":{"p":"ಪ್ಯಾಲೇಸ್ಟೇನಿಯನ್ ಪ್ರದೇಶಗಳು","s":"ಪ್ಯಾಲೆಸ್ಟೈನ್"},"PT":{"p":"ಪೋರ್ಚುಗಲ್"},"PW":{"p":"ಪಲಾವು"},"PY":{"p":"ಪರಾಗ್ವೇ"},"QA":{"p":"ಖತಾರ್"},"QO":{"p":"ಔಟ್ ಲೈಯಿಂಗ್ ಓಷಿಯಾನಿಯಾ"},"RE":{"p":"ರೀಯೂನಿಯನ್"},"RO":{"p":"ರೊಮೇನಿಯಾ"},"RS":{"p":"ಸೆರ್ಬಿಯಾ"},"RU":{"p":"ರಷ್ಯಾ"},"RW":{"p":"ರುವಾಂಡಾ"},"SA":{"p":"ಸೌದಿ ಅರೇಬಿಯಾ"},"SB":{"p":"ಸೊಲೊಮನ್ ದ್ವೀಪಗಳು"},"SC":{"p":"ಸೀಶೆಲ್ಲೆಸ್"},"SD":{"p":"ಸೂಡಾನ್"},"SE":{"p":"ಸ್ವೀಡನ್"},"SG":{"p":"ಸಿಂಗಾಪುರ್"},"SH":{"p":"ಸೇಂಟ್ ಹೆಲೆನಾ"},"SI":{"p":"ಸ್ಲೋವೇನಿಯಾ"},"SJ":{"p":"ಸ್ವಾಲ್ಬಾರ್ಡ್ ಮತ್ತು ಜಾನ್ ಮೆಯನ್"},"SK":{"p":"ಸ್ಲೋವಾಕಿಯಾ"},"SL":{"p":"ಸಿಯೆರ್ರಾ ಲಿಯೋನ್"},"SM":{"p":"ಸ್ಯಾನ್ ಮೆರಿನೋ"},"SN":{"p":"ಸೆನೆಗಲ್"},"SO":{"p":"ಸೊಮಾಲಿಯಾ"},"SR":{"p":"ಸುರಿನಾಮ"},"SS":{"p":"ದಕ್ಷಿಣ ಸೂಡಾನ್"},"ST":{"p":"ಸಾವೋ ಟೋಮ್ ಮತ್ತು ಪ್ರಿನ್ಸಿಪಿ"},"SV":{"p":"ಎಲ್ ಸಾಲ್ವೇಡಾರ್"},"SX":{"p":"ಸಿಂಟ್ ಮಾರ್ಟೆನ್"},"SY":{"p":"ಸಿರಿಯಾ"},"SZ":{"p":"ಸ್ವಾಜಿಲ್ಯಾಂಡ್"},"TA":{"p":"ಟ್ರಿಸ್ತನ್ ಡಾ ಕುನ್ಹಾ"},"TC":{"p":"ಟರ್ಕ್ಸ್ ಮತ್ತು ಕೈಕೋಸ್ ದ್ವೀಪಗಳು"},"TD":{"p":"ಚಾದ್"},"TF":{"p":"ಫ್ರೆಂಚ್ ದಕ್ಷಿಣ ಪ್ರದೇಶಗಳು"},"TG":{"p":"ಟೋಗೋ"},"TH":{"p":"ಥೈಲ್ಯಾಂಡ್"},"TJ":{"p":"ತಜಿಕಿಸ್ತಾನ್"},"TK":{"p":"ಟೊಕೆಲಾವ್"},"TL":{"p":"ಪೂರ್ವ ತಿಮೋರ್","v":"ಪೂರ್ವ ಟಿಮೋರ್"},"TM":{"p":"ತುರ್ಕಮೆನಿಸ್ತಾನ್"},"TN":{"p":"ಟುನಿಶಿಯಾ"},"TO":{"p":"ಟೊಂಗ"},"TR":{"p":"ಟರ್ಕಿ"},"TT":{"p":"ಟ್ರಿನಿಡಾಡ್ ಮತ್ತು ಟೊಬಾಗೊ"},"TV":{"p":"ಟುವಾಲು"},"TW":{"p":"ಥೈವಾನ್"},"TZ":{"p":"ತಾಂಜೇನಿಯಾ"},"UA":{"p":"ಉಕ್ರೈನ್"},"UG":{"p":"ಉಗಾಂಡಾ"},"UM":{"p":"ಯುಎಸ್‌. ಔಟ್‌ಲೇಯಿಂಗ್ ದ್ವೀಪಗಳು"},"UN":{"p":"ಸಂಯುಕ್ತ ಸಂಸ್ಥಾನಗಳು","s":"ಯುಎನ್"},"US":{"p":"ಅಮೇರಿಕಾ ಸಂಯುಕ್ತ ಸಂಸ್ಥಾನ","s":"ಯು.ಎಸ್"},"UY":{"p":"ಉರುಗ್ವೇ"},"UZ":{"p":"ಉಜ್ಬೇಕಿಸ್ಥಾನ್"},"VA":{"p":"ವ್ಯಾಟಿಕನ್"},"VC":{"p":"ಸೇಂಟ್. ವಿನ್ಸೆಂಟ್ ಮತ್ತು ಗ್ರೆನೆಡೈನ್ಸ್"},"VE":{"p":"ವೆನೆಜುವೆಲಾ"},"VG":{"p":"ಬ್ರಿಟಿಷ್ ವರ್ಜಿನ್ ದ್ವೀಪಗಳು"},"VI":{"p":"ಯು.ಎಸ್. ವರ್ಜಿನ್ ದ್ವೀಪಗಳು"},"VN":{"p":"ವಿಯೇಟ್ನಾಮ್"},"VU":{"p":"ವನೌಟು"},"WF":{"p":"ವಾಲಿಸ್ ಮತ್ತು ಫುಟುನಾ"},"WS":{"p":"ಸಮೋವಾ"},"XK":{"p":"ಕೊಸೊವೊ"},"YE":{"p":"ಯೆಮನ್"},"YT":{"p":"ಮಯೊಟ್ಟೆ"},"ZA":{"p":"ದಕ್ಷಿಣ ಆಫ್ರಿಕಾ"},"ZM":{"p":"ಝಾಂಬಿಯಾ"},"ZW":{"p":"ಜಿಂಬಾಬ್ವೆ"},"ZZ":{"p":"ಅಜ್ಞಾತ ಪ್ರದೇಶ"}}
